augraphy/__init__.py
augraphy/augmentations/__init__.py
augraphy/augmentations/badphotocopy.py
augraphy/augmentations/bindingsandfasteners.py
augraphy/augmentations/bleedthrough.py
augraphy/augmentations/bookbinding.py
augraphy/augmentations/brightness.py
augraphy/augmentations/brightnesstexturize.py
augraphy/augmentations/colorpaper.py
augraphy/augmentations/colorshift.py
augraphy/augmentations/delaunay.py
augraphy/augmentations/depthsimulatedblur.py
augraphy/augmentations/dirtydrum.py
augraphy/augmentations/dirtyrollers.py
augraphy/augmentations/dirtyscreen.py
augraphy/augmentations/dithering.py
augraphy/augmentations/dotmatrix.py
augraphy/augmentations/doubleexposure.py
augraphy/augmentations/faxify.py
augraphy/augmentations/folding.py
augraphy/augmentations/gamma.py
augraphy/augmentations/geometric.py
augraphy/augmentations/glitcheffect.py
augraphy/augmentations/hollow.py
augraphy/augmentations/inkbleed.py
augraphy/augmentations/inkcolorswap.py
augraphy/augmentations/inkmottling.py
augraphy/augmentations/inkshifter.py
augraphy/augmentations/jpeg.py
augraphy/augmentations/lcdscreenpattern.py
augraphy/augmentations/lensflare.py
augraphy/augmentations/letterpress.py
augraphy/augmentations/lib.py
augraphy/augmentations/lightinggradient.py
augraphy/augmentations/linesdegradation.py
augraphy/augmentations/lowinkline.py
augraphy/augmentations/lowinkperiodiclines.py
augraphy/augmentations/lowinkrandomlines.py
augraphy/augmentations/lowlightnoise.py
augraphy/augmentations/markup.py
augraphy/augmentations/moire.py
augraphy/augmentations/noisetexturize.py
augraphy/augmentations/noisylines.py
augraphy/augmentations/pageborder.py
augraphy/augmentations/quasicrystal.py
augraphy/augmentations/reflectedlight.py
augraphy/augmentations/rescale.py
augraphy/augmentations/scribbles.py
augraphy/augmentations/sectionshift.py
augraphy/augmentations/shadowcast.py
augraphy/augmentations/squish.py
augraphy/augmentations/stains.py
augraphy/augmentations/subtlenoise.py
augraphy-8.2.6.dist-info/LICENSE
augraphy-8.2.6.dist-info/METADATA
augraphy-8.2.6.dist-info/WHEEL
augraphy-8.2.6.dist-info/top_level.txt
augraphy-8.2.6.dist-info/RECORD
