Metadata-Version: 2.1
Name: augraphy
Version: 8.2.6
Summary: Augmentation pipeline for rendering synthetic paper printing and scanning processes
Home-page: https://github.com/sparkfish/augraphy
Author: Sparkfish LLC
Author-email: packages@sparkfish.com
License: UNKNOWN
Project-URL: Bug Tracker, https://github.com/sparkfish/augraphy/issues
Platform: UNKNOWN
Classifier: Programming Language :: Python :: 3
Classifier: License :: OSI Approved :: MIT License
Classifier: Operating System :: OS Independent
Requires-Python: >=3.8
